{"name":"1. New client with Analysis in Emma JM","id":"regression-jm;1.-new-client-with-analysis-in-emma-jm","scenarioId":"emma/jm/uat/regressionJm:1. New client with Analysis in Emma JM","methodName":"1. New client with Analysis in Emma JM","testSteps":[{"number":1,"description":"1: 1. New client with Analysis in Emma JM ({country\u003dJamaica, store\u003dCOU JM Port Maria, typeId\u003dTRN, documentId\u003d825126700, firstName\u003dJULIO, secondName\u003dRAUL, firstLastName\u003dSAlINAS, secondLastName\u003dGALVEZ, gender\u003dMale, birthDate\u003d2001-JAN-15, areaCode\u003d876, numberMovil\u003d1598788, email\u003dr@g.c, marriedStatus\u003dCommon Law, dependsNumber\u003d3, address\u003d79-80 A SUPER ROAD, frecuencyPaid\u003dFortnightly, income\u003d2000, occupation\u003dCivil Servant, companyName\u003dUNICOMER SAC, employStartDate\u003d2020-MAY-7, companyParish\u003dManchester, companyDistrict\u003dColeyville, jobMainActivity\u003dCommisions, department\u003dSt Andre, district\u003dContent Gap, streetResidence\u003dX5X9+QQQ, LAS VEGAS, referenceResidence\u003dWhat is D\u0026Bs, currentDateAddress\u003d2021-JAN-1, residentStatus\u003dRent, nameReference1\u003dHERNAN PAREDES, relationship1\u003dCoworker, areaCodeRef\u003d876, numberReference1\u003d1593645, referenceLocation\u003d79 -81a Road UNITED, nameReference2\u003dJULIAN ALVAREZ, relationship2\u003dFather, numberReference2\u003d3697415, streetWork\u003dPRINCIPAL STREET, message\u003dCredit application completed!})","duration":223146,"startTime":"2024-02-06T06:48:12.251833800-05:00[America/Lima]","screenshots":[{"screenshot":"59938f93b56696d6534094602fb53e4b6a0e86a9926ac6ed7e409fd522e983fc.png","timeStamp":1707220315398,"screenshotName":"59938f93b56696d6534094602fb53e4b6a0e86a9926ac6ed7e409fd522e983fc.png"}],"result":"SUCCESS","precondition":false,"level":0,"lineNumber":18,"children":[{"number":2,"description":"Given DataTable customer data\r\n| typeId | documentId | store | firstName | secondName | firstLastName | secondLastName | numberMovil | email | birthDate | areaCode | gender | dependsNumber | marriedStatus | address | frecuencyPaid | income | occupation | companyName | mployStartDate | companyParish | companyDistrict | jobMainActivity | department | district | streetResidence | referenceResidence | currentDateAddress | residentStatus | employStartDate | nameReference1 | relationship1 | areaCodeRef | numberReference1 | referenceLocation | nameReference2 | relationship2 | numberReference2 | streetWork |\r\n| TRN | 825126700 | COU JM Port Maria | JULIO | RAUL | SAlINAS | GALVEZ | 1598788 | r@g.c | 2001-JAN-15 | 876 | Male | 3 | Common Law | 79-80 A SUPER ROAD | Fortnightly | 2000 | Civil Servant | UNICOMER SAC | 2023-SEP-18 | Manchester | Coleyville | Commisions | St Andre | Content Gap | X5X9+QQQ, LAS VEGAS | What is D\u0026Bs | 2021-JAN-1 | Rent | 2023-SEP-18 | HERNAN PAREDES | Coworker | 876 | 1593645 | 79 -81a Road UNITED | JULIAN ALVAREZ | Father | 3697415 | PRINCIPAL STREET |","duration":707,"startTime":"2024-02-06T06:48:18.895958700-05:00[America/Lima]","screenshots":[{"screenshot":"5b84425f7e0ee06fe5ab14624dbe28050336ffaae05a3a36881bc67fd80c59bb.png","htmlSource":"pagesource15456463828937376173.html","timeStamp":1707220099513,"screenshotName":"5b84425f7e0ee06fe5ab14624dbe28050336ffaae05a3a36881bc67fd80c59bb.png"}],"result":"SUCCESS","precondition":false,"level":1},{"number":3,"description":"Given the user into EMMA in \"Jamaica\" with credentials","duration":25443,"startTime":"2024-02-06T06:48:19.606306200-05:00[America/Lima]","screenshots":[{"screenshot":"5b84425f7e0ee06fe5ab14624dbe28050336ffaae05a3a36881bc67fd80c59bb.png","htmlSource":"pagesource15844270312310451016.html","timeStamp":1707220099630,"screenshotName":"5b84425f7e0ee06fe5ab14624dbe28050336ffaae05a3a36881bc67fd80c59bb.png"},{"screenshot":"0bc59725a9170dcbd6a2f44d29ba47b8ffe66acf1c3ce5bcc5a19aaa79480961.png","timeStamp":1707220125049,"screenshotName":"0bc59725a9170dcbd6a2f44d29ba47b8ffe66acf1c3ce5bcc5a19aaa79480961.png"}],"result":"SUCCESS","precondition":false,"level":1,"children":[{"number":4,"description":"Admin navigate sit","duration":25022,"startTime":"2024-02-06T06:48:20.014077200-05:00[America/Lima]","screenshots":[{"screenshot":"5b84425f7e0ee06fe5ab14624dbe28050336ffaae05a3a36881bc67fd80c59bb.png","htmlSource":"pagesource13013847899495442094.html","timeStamp":1707220100112,"screenshotName":"5b84425f7e0ee06fe5ab14624dbe28050336ffaae05a3a36881bc67fd80c59bb.png"},{"screenshot":"0bc59725a9170dcbd6a2f44d29ba47b8ffe66acf1c3ce5bcc5a19aaa79480961.png","timeStamp":1707220125036,"screenshotName":"0bc59725a9170dcbd6a2f44d29ba47b8ffe66acf1c3ce5bcc5a19aaa79480961.png"}],"result":"SUCCESS","precondition":false,"level":2,"children":[{"number":5,"description":"admin opens the browser at https://credits-uat.unicomer.com/","duration":1921,"startTime":"2024-02-06T06:48:20.128111500-05:00[America/Lima]","screenshots":[{"screenshot":"5b84425f7e0ee06fe5ab14624dbe28050336ffaae05a3a36881bc67fd80c59bb.png","htmlSource":"pagesource18110978546871409600.html","timeStamp":1707220100164,"screenshotName":"5b84425f7e0ee06fe5ab14624dbe28050336ffaae05a3a36881bc67fd80c59bb.png"},{"screenshot":"c87ac47b522e51f850628520f899190cc264212c10221e010db6ba224e71b5e6.png","timeStamp":1707220102049,"screenshotName":"c87ac47b522e51f850628520f899190cc264212c10221e010db6ba224e71b5e6.png"}],"result":"SUCCESS","precondition":false,"level":3},{"number":6,"description":"admin clicks on BUTTON LOGIN","duration":3810,"startTime":"2024-02-06T06:48:22.136421500-05:00[America/Lima]","screenshots":[{"screenshot":"cfba96015123b73e35665af285410140b1e56c77cfb88708f0e35dddcf302059.png","htmlSource":"pagesource3065624014241352553.html","timeStamp":1707220102674,"screenshotName":"cfba96015123b73e35665af285410140b1e56c77cfb88708f0e35dddcf302059.png"},{"screenshot":"47eb3f0f68d7dd8318370d978795d8ae963ba8866654d18acbb8c85cc59e1ccb.png","timeStamp":1707220105947,"screenshotName":"47eb3f0f68d7dd8318370d978795d8ae963ba8866654d18acbb8c85cc59e1ccb.png"}],"result":"SUCCESS","precondition":false,"level":3},{"number":7,"description":"admin enters \u0027ventas_evaluacioncreditojm@unicomer.com\u0027 into ENTER THE USER","duration":746,"startTime":"2024-02-06T06:48:25.993465700-05:00[America/Lima]","screenshots":[{"screenshot":"47eb3f0f68d7dd8318370d978795d8ae963ba8866654d18acbb8c85cc59e1ccb.png","htmlSource":"pagesource17525280448965972864.html","timeStamp":1707220106144,"screenshotName":"47eb3f0f68d7dd8318370d978795d8ae963ba8866654d18acbb8c85cc59e1ccb.png"},{"screenshot":"8392177fbbd7ac2222eeb27eb2515a8408c1a218b36c8dad590f7116b07880e4.png","timeStamp":1707220106739,"screenshotName":"8392177fbbd7ac2222eeb27eb2515a8408c1a218b36c8dad590f7116b07880e4.png"}],"result":"SUCCESS","precondition":false,"level":3},{"number":8,"description":"admin clicks on BUTTON SUBMIT","duration":443,"startTime":"2024-02-06T06:48:26.749330300-05:00[America/Lima]","screenshots":[{"screenshot":"8392177fbbd7ac2222eeb27eb2515a8408c1a218b36c8dad590f7116b07880e4.png","htmlSource":"pagesource18191870020742346976.html","timeStamp":1707220106832,"screenshotName":"8392177fbbd7ac2222eeb27eb2515a8408c1a218b36c8dad590f7116b07880e4.png"},{"screenshot":"ae24c91e3c264c59985e4ae502aa1f3dd1357801e93895e4662f36eeb0d48597.png","timeStamp":1707220107191,"screenshotName":"ae24c91e3c264c59985e4ae502aa1f3dd1357801e93895e4662f36eeb0d48597.png"}],"result":"SUCCESS","precondition":false,"level":3},{"number":9,"description":"admin enters \u0027Unicomer23\u0027 into ENTER THE PASSWORD","duration":678,"startTime":"2024-02-06T06:48:27.203577500-05:00[America/Lima]","screenshots":[{"screenshot":"ae24c91e3c264c59985e4ae502aa1f3dd1357801e93895e4662f36eeb0d48597.png","htmlSource":"pagesource11650641008717828731.html","timeStamp":1707220107270,"screenshotName":"ae24c91e3c264c59985e4ae502aa1f3dd1357801e93895e4662f36eeb0d48597.png"},{"screenshot":"a1e5532f1b9f18004d352a15e46260086b390981bd30514019b1bc869ea8d8de.png","timeStamp":1707220107881,"screenshotName":"a1e5532f1b9f18004d352a15e46260086b390981bd30514019b1bc869ea8d8de.png"}],"result":"SUCCESS","precondition":false,"level":3},{"number":10,"description":"admin clicks on BUTTON SUBMIT","duration":1572,"startTime":"2024-02-06T06:48:27.888786-05:00[America/Lima]","screenshots":[{"screenshot":"a1e5532f1b9f18004d352a15e46260086b390981bd30514019b1bc869ea8d8de.png","htmlSource":"pagesource12538393632507357702.html","timeStamp":1707220107934,"screenshotName":"a1e5532f1b9f18004d352a15e46260086b390981bd30514019b1bc869ea8d8de.png"},{"screenshot":"561d80eecafbef1564039ef3102832d1417eed75193da220231f4de94d0fe835.png","timeStamp":1707220109461,"screenshotName":"561d80eecafbef1564039ef3102832d1417eed75193da220231f4de94d0fe835.png"}],"result":"SUCCESS","precondition":false,"level":3},{"number":11,"description":"admin clicks on BUTTON NOT ACTIVE","duration":2401,"startTime":"2024-02-06T06:48:39.492188500-05:00[America/Lima]","screenshots":[{"screenshot":"c99cbe206f2ec7684583e077e91e3a8cecff41c7f1bf9ba070527cad98d55225.png","htmlSource":"pagesource12513312895309894041.html","timeStamp":1707220119661,"screenshotName":"c99cbe206f2ec7684583e077e91e3a8cecff41c7f1bf9ba070527cad98d55225.png"},{"screenshot":"5b84425f7e0ee06fe5ab14624dbe28050336ffaae05a3a36881bc67fd80c59bb.png","timeStamp":1707220121893,"screenshotName":"5b84425f7e0ee06fe5ab14624dbe28050336ffaae05a3a36881bc67fd80c59bb.png"}],"result":"SUCCESS","precondition":false,"level":3}]}]},{"number":12,"description":"And select the country emma","duration":9504,"startTime":"2024-02-06T06:48:45.051431-05:00[America/Lima]","screenshots":[{"screenshot":"0bc59725a9170dcbd6a2f44d29ba47b8ffe66acf1c3ce5bcc5a19aaa79480961.png","htmlSource":"pagesource11494588528578002855.html","timeStamp":1707220125097,"screenshotName":"0bc59725a9170dcbd6a2f44d29ba47b8ffe66acf1c3ce5bcc5a19aaa79480961.png"},{"screenshot":"a29c43c8da20ec13951967ad7f0e2e6f0a54656a898aa3df3bd932f82bffd412.png","timeStamp":1707220134556,"screenshotName":"a29c43c8da20ec13951967ad7f0e2e6f0a54656a898aa3df3bd932f82bffd412.png"}],"result":"SUCCESS","precondition":false,"level":1,"children":[{"number":13,"description":"Admin select country","duration":9435,"startTime":"2024-02-06T06:48:45.115314900-05:00[America/Lima]","screenshots":[{"screenshot":"0bc59725a9170dcbd6a2f44d29ba47b8ffe66acf1c3ce5bcc5a19aaa79480961.png","htmlSource":"pagesource9308550574935994472.html","timeStamp":1707220125807,"screenshotName":"0bc59725a9170dcbd6a2f44d29ba47b8ffe66acf1c3ce5bcc5a19aaa79480961.png"},{"screenshot":"a29c43c8da20ec13951967ad7f0e2e6f0a54656a898aa3df3bd932f82bffd412.png","timeStamp":1707220134551,"screenshotName":"a29c43c8da20ec13951967ad7f0e2e6f0a54656a898aa3df3bd932f82bffd412.png"}],"result":"SUCCESS","precondition":false,"level":2,"children":[{"number":14,"description":"admin clicks on ALERT COUNTRY","duration":525,"startTime":"2024-02-06T06:48:48.808510400-05:00[America/Lima]","screenshots":[{"screenshot":"0bc59725a9170dcbd6a2f44d29ba47b8ffe66acf1c3ce5bcc5a19aaa79480961.png","htmlSource":"pagesource10086714016024017061.html","timeStamp":1707220129024,"screenshotName":"0bc59725a9170dcbd6a2f44d29ba47b8ffe66acf1c3ce5bcc5a19aaa79480961.png"},{"screenshot":"48c9e9053a5c2fb82d965f74107758b38ecda964b55e791c982b6188e5598098.png","timeStamp":1707220129334,"screenshotName":"48c9e9053a5c2fb82d965f74107758b38ecda964b55e791c982b6188e5598098.png"}],"result":"SUCCESS","precondition":false,"level":3},{"number":15,"description":"admin clicks on BUTTON CONTINUE JM","duration":431,"startTime":"2024-02-06T06:48:51.475874700-05:00[America/Lima]","screenshots":[{"screenshot":"87ed69ef2b0557c5e6012215ee06082f7df434534b44d446d03d250e7cde1145.png","htmlSource":"pagesource3370969546880085232.html","timeStamp":1707220131665,"screenshotName":"87ed69ef2b0557c5e6012215ee06082f7df434534b44d446d03d250e7cde1145.png"},{"screenshot":"a29c43c8da20ec13951967ad7f0e2e6f0a54656a898aa3df3bd932f82bffd412.png","timeStamp":1707220131907,"screenshotName":"a29c43c8da20ec13951967ad7f0e2e6f0a54656a898aa3df3bd932f82bffd412.png"}],"result":"SUCCESS","precondition":false,"level":3}]}]},{"number":16,"description":"And select the store in emma","duration":4577,"startTime":"2024-02-06T06:48:54.556199800-05:00[America/Lima]","screenshots":[{"screenshot":"a29c43c8da20ec13951967ad7f0e2e6f0a54656a898aa3df3bd932f82bffd412.png","htmlSource":"pagesource10087853361801662174.html","timeStamp":1707220134612,"screenshotName":"a29c43c8da20ec13951967ad7f0e2e6f0a54656a898aa3df3bd932f82bffd412.png"},{"screenshot":"5b84425f7e0ee06fe5ab14624dbe28050336ffaae05a3a36881bc67fd80c59bb.png","timeStamp":1707220139134,"screenshotName":"5b84425f7e0ee06fe5ab14624dbe28050336ffaae05a3a36881bc67fd80c59bb.png"}],"result":"SUCCESS","precondition":false,"level":1,"children":[{"number":17,"description":"Admin select store","duration":4505,"startTime":"2024-02-06T06:48:54.618306400-05:00[America/Lima]","screenshots":[{"screenshot":"a29c43c8da20ec13951967ad7f0e2e6f0a54656a898aa3df3bd932f82bffd412.png","htmlSource":"pagesource7087814637793888561.html","timeStamp":1707220135265,"screenshotName":"a29c43c8da20ec13951967ad7f0e2e6f0a54656a898aa3df3bd932f82bffd412.png"},{"screenshot":"5b84425f7e0ee06fe5ab14624dbe28050336ffaae05a3a36881bc67fd80c59bb.png","timeStamp":1707220139123,"screenshotName":"5b84425f7e0ee06fe5ab14624dbe28050336ffaae05a3a36881bc67fd80c59bb.png"}],"result":"SUCCESS","precondition":false,"level":2,"children":[{"number":18,"description":"admin clicks on ALERT STORE","duration":286,"startTime":"2024-02-06T06:48:55.268734200-05:00[America/Lima]","screenshots":[{"screenshot":"a29c43c8da20ec13951967ad7f0e2e6f0a54656a898aa3df3bd932f82bffd412.png","htmlSource":"pagesource10113437288793600193.html","timeStamp":1707220135307,"screenshotName":"a29c43c8da20ec13951967ad7f0e2e6f0a54656a898aa3df3bd932f82bffd412.png"},{"screenshot":"993297831d20f97e66a7e0c35f26efced5440453b9804bb33b01d1e8f210fc56.png","timeStamp":1707220135554,"screenshotName":"993297831d20f97e66a7e0c35f26efced5440453b9804bb33b01d1e8f210fc56.png"}],"result":"SUCCESS","precondition":false,"level":3},{"number":19,"description":"admin clicks on BUTTON CONTINUE JM","duration":350,"startTime":"2024-02-06T06:48:56.676285800-05:00[America/Lima]","screenshots":[{"screenshot":"a0cf5a212e5210754628b270abafeb4d8f63df3b895067520664a13370f531b0.png","htmlSource":"pagesource18012775065509176003.html","timeStamp":1707220136805,"screenshotName":"a0cf5a212e5210754628b270abafeb4d8f63df3b895067520664a13370f531b0.png"},{"screenshot":"e2ebdf09b4e4b0805e1effe686c166ffe487dbf9f95a67be2747d666c13b9edd.png","timeStamp":1707220137026,"screenshotName":"e2ebdf09b4e4b0805e1effe686c166ffe487dbf9f95a67be2747d666c13b9edd.png"}],"result":"SUCCESS","precondition":false,"level":3}]}]},{"number":20,"description":"When validate the document ID dose not exist","duration":6258,"startTime":"2024-02-06T06:48:59.134146800-05:00[America/Lima]","screenshots":[{"screenshot":"5b84425f7e0ee06fe5ab14624dbe28050336ffaae05a3a36881bc67fd80c59bb.png","htmlSource":"pagesource6351733833964690899.html","timeStamp":1707220139174,"screenshotName":"5b84425f7e0ee06fe5ab14624dbe28050336ffaae05a3a36881bc67fd80c59bb.png"},{"screenshot":"0bd6a84abb0b4bee8fafda764b59d24ac32ff6b6c36cfc298e4efa93e4cbab1b.png","timeStamp":1707220145393,"screenshotName":"0bd6a84abb0b4bee8fafda764b59d24ac32ff6b6c36cfc298e4efa93e4cbab1b.png"}],"result":"SUCCESS","precondition":false,"level":1,"children":[{"number":21,"description":"Admin search document","duration":6198,"startTime":"2024-02-06T06:48:59.182010900-05:00[America/Lima]","screenshots":[{"screenshot":"5b84425f7e0ee06fe5ab14624dbe28050336ffaae05a3a36881bc67fd80c59bb.png","htmlSource":"pagesource4341872232581494136.html","timeStamp":1707220139282,"screenshotName":"5b84425f7e0ee06fe5ab14624dbe28050336ffaae05a3a36881bc67fd80c59bb.png"},{"screenshot":"0bd6a84abb0b4bee8fafda764b59d24ac32ff6b6c36cfc298e4efa93e4cbab1b.png","timeStamp":1707220145380,"screenshotName":"0bd6a84abb0b4bee8fafda764b59d24ac32ff6b6c36cfc298e4efa93e4cbab1b.png"}],"result":"SUCCESS","precondition":false,"level":2,"children":[{"number":22,"description":"admin enters \u0027825126700\u0027 into INSERT DOCUMENT","duration":392,"startTime":"2024-02-06T06:49:01.290195200-05:00[America/Lima]","screenshots":[{"screenshot":"f0e9dace670763c5a15dd1f25c43e5558ebddaad7654a74922a8597cf6a8e986.png","htmlSource":"pagesource2706506687135688056.html","timeStamp":1707220141427,"screenshotName":"f0e9dace670763c5a15dd1f25c43e5558ebddaad7654a74922a8597cf6a8e986.png"},{"screenshot":"5ae91f52291032e0e4266d3f7cf74b3d67623b90414407be3ceaef56c15f0e34.png","timeStamp":1707220141682,"screenshotName":"5ae91f52291032e0e4266d3f7cf74b3d67623b90414407be3ceaef56c15f0e34.png"}],"result":"SUCCESS","precondition":false,"level":3},{"number":23,"description":"admin clicks on BUTTON TO CHECK IF CLIENT ALREADY EXIST","duration":244,"startTime":"2024-02-06T06:49:01.688502700-05:00[America/Lima]","screenshots":[{"screenshot":"5ae91f52291032e0e4266d3f7cf74b3d67623b90414407be3ceaef56c15f0e34.png","htmlSource":"pagesource10595429445546648048.html","timeStamp":1707220141731,"screenshotName":"5ae91f52291032e0e4266d3f7cf74b3d67623b90414407be3ceaef56c15f0e34.png"},{"screenshot":"aa779255c8e9968d13e98c414c8e99863aa7a805b808c104eb508d20ebc4998c.png","timeStamp":1707220141933,"screenshotName":"aa779255c8e9968d13e98c414c8e99863aa7a805b808c104eb508d20ebc4998c.png"}],"result":"SUCCESS","precondition":false,"level":3},{"number":24,"description":"admin clicks on BUTTON NEW CREDIT APPLICATION","duration":2411,"startTime":"2024-02-06T06:49:02.959334300-05:00[America/Lima]","screenshots":[{"screenshot":"d714d50697a308a1b07a469507377f610fd2b3b1e482143ec45e617fb0d47790.png","htmlSource":"pagesource14604432827604669045.html","timeStamp":1707220143134,"screenshotName":"d714d50697a308a1b07a469507377f610fd2b3b1e482143ec45e617fb0d47790.png"},{"screenshot":"0bd6a84abb0b4bee8fafda764b59d24ac32ff6b6c36cfc298e4efa93e4cbab1b.png","timeStamp":1707220145370,"screenshotName":"0bd6a84abb0b4bee8fafda764b59d24ac32ff6b6c36cfc298e4efa93e4cbab1b.png"}],"result":"SUCCESS","precondition":false,"level":3}]}]},{"number":25,"description":"And user enter basic information for Document validation section","duration":146774,"startTime":"2024-02-06T06:49:05.394485200-05:00[America/Lima]","screenshots":[{"screenshot":"0bd6a84abb0b4bee8fafda764b59d24ac32ff6b6c36cfc298e4efa93e4cbab1b.png","htmlSource":"pagesource7494099978537322968.html","timeStamp":1707220145441,"screenshotName":"0bd6a84abb0b4bee8fafda764b59d24ac32ff6b6c36cfc298e4efa93e4cbab1b.png"},{"screenshot":"1733adfd3bf64d98c1ab393393c29c69955413842509a1ce9085eab8f43a8954.png","timeStamp":1707220292169,"screenshotName":"1733adfd3bf64d98c1ab393393c29c69955413842509a1ce9085eab8f43a8954.png"}],"result":"SUCCESS","precondition":false,"level":1,"children":[{"number":26,"description":"Admin document validation","duration":45305,"startTime":"2024-02-06T06:49:05.446705300-05:00[America/Lima]","screenshots":[{"screenshot":"cfdab8cda8cf9eac4261910c15d432af8fe7ee164621de20ba68e00f531b86af.png","htmlSource":"pagesource3333941486620588384.html","timeStamp":1707220146095,"screenshotName":"cfdab8cda8cf9eac4261910c15d432af8fe7ee164621de20ba68e00f531b86af.png"},{"screenshot":"c1ccd10f1a1d63809f3cfeb0c8e06be08ebd4a0bafb4abd62f80be9886415a33.png","timeStamp":1707220190752,"screenshotName":"c1ccd10f1a1d63809f3cfeb0c8e06be08ebd4a0bafb4abd62f80be9886415a33.png"}],"result":"SUCCESS","precondition":false,"level":2,"children":[{"number":27,"description":"Admin write into","duration":3145,"startTime":"2024-02-06T06:49:07.139553200-05:00[America/Lima]","screenshots":[{"screenshot":"71cdf5be5d92f51a8acef05e354140a4ddee12a1486624a40e1d99f44aa14aac.png","htmlSource":"pagesource4387774150329712006.html","timeStamp":1707220147277,"screenshotName":"71cdf5be5d92f51a8acef05e354140a4ddee12a1486624a40e1d99f44aa14aac.png"},{"screenshot":"c81a71540fb16ad16b5d5f129e92036cee7f769c11bdc0c0eefd2e74955cfdb2.png","timeStamp":1707220150285,"screenshotName":"c81a71540fb16ad16b5d5f129e92036cee7f769c11bdc0c0eefd2e74955cfdb2.png"}],"result":"SUCCESS","precondition":false,"level":3,"children":[{"number":28,"description":"admin enters \u0027JULIO\u0027 into INPUT NAME","duration":1822,"startTime":"2024-02-06T06:49:07.286211100-05:00[America/Lima]","screenshots":[{"screenshot":"626bbcea9debbfce055d499f89c50c68d5ab97a51936979478a1fa548a3caf85.png","htmlSource":"pagesource3836803476346291755.html","timeStamp":1707220147425,"screenshotName":"626bbcea9debbfce055d499f89c50c68d5ab97a51936979478a1fa548a3caf85.png"},{"screenshot":"72b0c2442376281255222b7f339218b7d4d8d4b4afb529467d24d42347678f60.png","timeStamp":1707220149108,"screenshotName":"72b0c2442376281255222b7f339218b7d4d8d4b4afb529467d24d42347678f60.png"}],"result":"SUCCESS","precondition":false,"level":4},{"number":29,"description":"admin enters \u0027JULIO\u0027 into INPUT NAME","duration":398,"startTime":"2024-02-06T06:49:09.203505900-05:00[America/Lima]","screenshots":[{"screenshot":"c250a176bd574b5057d17147f6c996a61de27a0543f8fc7cb6b11cfb30683510.png","htmlSource":"pagesource17099249700425027233.html","timeStamp":1707220149377,"screenshotName":"c250a176bd574b5057d17147f6c996a61de27a0543f8fc7cb6b11cfb30683510.png"},{"screenshot":"86cef52fab04350b9ef47bb0aab2b9baeb4d231ce1561132c694be19e2513405.png","timeStamp":1707220149602,"screenshotName":"86cef52fab04350b9ef47bb0aab2b9baeb4d231ce1561132c694be19e2513405.png"}],"result":"SUCCESS","precondition":false,"level":4}]},{"number":30,"description":"admin enters \u0027RAUL\u0027 into INPUT SECOND NAME","duration":314,"startTime":"2024-02-06T06:49:10.292113400-05:00[America/Lima]","screenshots":[{"screenshot":"c81a71540fb16ad16b5d5f129e92036cee7f769c11bdc0c0eefd2e74955cfdb2.png","htmlSource":"pagesource15292776068411062148.html","timeStamp":1707220150336,"screenshotName":"c81a71540fb16ad16b5d5f129e92036cee7f769c11bdc0c0eefd2e74955cfdb2.png"},{"screenshot":"1b815721a9e9717bba766614e5369dee64449c0d83f5afa1d158327102a0d410.png","timeStamp":1707220150607,"screenshotName":"1b815721a9e9717bba766614e5369dee64449c0d83f5afa1d158327102a0d410.png"}],"result":"SUCCESS","precondition":false,"level":3},{"number":31,"description":"admin enters \u0027SAlINAS\u0027 into INPUT THE LAST NAME","duration":962,"startTime":"2024-02-06T06:49:11.620956200-05:00[America/Lima]","screenshots":[{"screenshot":"2aadadeb5b97cbbf435bd9084887f98a333585a3cf49a555dcfb57492b11fe0b.png","htmlSource":"pagesource16731880631698932034.html","timeStamp":1707220152263,"screenshotName":"2aadadeb5b97cbbf435bd9084887f98a333585a3cf49a555dcfb57492b11fe0b.png"},{"screenshot":"5fb839bdf06369554ff6ff8404366c3e3259d0614ab31f801999156aecdc0018.png","timeStamp":1707220152583,"screenshotName":"5fb839bdf06369554ff6ff8404366c3e3259d0614ab31f801999156aecdc0018.png"}],"result":"SUCCESS","precondition":false,"level":3},{"number":32,"description":"admin enters \u0027GALVEZ\u0027 into INPUT THE CLIENT SECOND LAST NAME","duration":368,"startTime":"2024-02-06T06:49:12.593855500-05:00[America/Lima]","screenshots":[{"screenshot":"5fb839bdf06369554ff6ff8404366c3e3259d0614ab31f801999156aecdc0018.png","htmlSource":"pagesource1632465642563674757.html","timeStamp":1707220152653,"screenshotName":"5fb839bdf06369554ff6ff8404366c3e3259d0614ab31f801999156aecdc0018.png"},{"screenshot":"00faa24fd4d1f4474f7a04727b8847157594a23046e7e45f7872b100e7b2e0cc.png","timeStamp":1707220152962,"screenshotName":"00faa24fd4d1f4474f7a04727b8847157594a23046e7e45f7872b100e7b2e0cc.png"}],"result":"SUCCESS","precondition":false,"level":3},{"number":33,"description":"admin clicks on DROPDOWN TO SELECT GENDER","duration":2339,"startTime":"2024-02-06T06:49:13.972369800-05:00[America/Lima]","screenshots":[{"screenshot":"ffde80bbedc3ca04ee41d2f4d36a9911675e9608660103d62b290e57e2f077a3.png","htmlSource":"pagesource8077898734446549931.html","timeStamp":1707220154656,"screenshotName":"ffde80bbedc3ca04ee41d2f4d36a9911675e9608660103d62b290e57e2f077a3.png"},{"screenshot":"732ae0d05b14d5793f2f8ac0dd046e18379d4e473328b8e7571bbf791e28dcc7.png","timeStamp":1707220156312,"screenshotName":"732ae0d05b14d5793f2f8ac0dd046e18379d4e473328b8e7571bbf791e28dcc7.png"}],"result":"SUCCESS","precondition":false,"level":3},{"number":34,"description":"admin clicks on BUTTON SELECT YEARS ","duration":1938,"startTime":"2024-02-06T06:49:17.419453900-05:00[America/Lima]","screenshots":[{"screenshot":"72eb423cf74d9ec433cb5d3ade44b22c45d6fbcc4162a65d803d2e1760c83453.png","htmlSource":"pagesource15600414284406934247.html","timeStamp":1707220157614,"screenshotName":"72eb423cf74d9ec433cb5d3ade44b22c45d6fbcc4162a65d803d2e1760c83453.png"},{"screenshot":"88edff16e8cf1cbd5c8ac4c3e6dcf3e869c67bd179b1bd0685ec2f62ba23eb95.png","timeStamp":1707220159357,"screenshotName":"88edff16e8cf1cbd5c8ac4c3e6dcf3e869c67bd179b1bd0685ec2f62ba23eb95.png"}],"result":"SUCCESS","precondition":false,"level":3},{"number":35,"description":"admin clicks on BUTTON BACK YEARS ","duration":375,"startTime":"2024-02-06T06:49:19.366326800-05:00[America/Lima]","screenshots":[{"screenshot":"88edff16e8cf1cbd5c8ac4c3e6dcf3e869c67bd179b1bd0685ec2f62ba23eb95.png","htmlSource":"pagesource10312990928336841377.html","timeStamp":1707220159438,"screenshotName":"88edff16e8cf1cbd5c8ac4c3e6dcf3e869c67bd179b1bd0685ec2f62ba23eb95.png"},{"screenshot":"1f7f3e6ca076d7c07401c61fc71f5bd5979955b00ad317ab11623a814980987a.png","timeStamp":1707220159741,"screenshotName":"1f7f3e6ca076d7c07401c61fc71f5bd5979955b00ad317ab11623a814980987a.png"}],"result":"SUCCESS","precondition":false,"level":3},{"number":36,"description":"admin clicks on DROPDOWN TO SELECT AREA CODE","duration":1884,"startTime":"2024-02-06T06:49:21.442238500-05:00[America/Lima]","screenshots":[{"screenshot":"6abea8c2ad78c1b050c26061ef289b8a943c4e70976038cefd6518215e79c2e4.png","htmlSource":"pagesource14680143220439439675.html","timeStamp":1707220161590,"screenshotName":"6abea8c2ad78c1b050c26061ef289b8a943c4e70976038cefd6518215e79c2e4.png"},{"screenshot":"3542c53c8956a56dadf9757ce7b30156bee32ad6f7ca94531369b9bcd86e5192.png","timeStamp":1707220163326,"screenshotName":"3542c53c8956a56dadf9757ce7b30156bee32ad6f7ca94531369b9bcd86e5192.png"}],"result":"SUCCESS","precondition":false,"level":3},{"number":37,"description":"admin enters \u00271598788\u0027 into INPUT PHONE NUMBER IN EMMA UAT JM","duration":417,"startTime":"2024-02-06T06:49:23.442961800-05:00[America/Lima]","screenshots":[{"screenshot":"3fb8b31db7c21753f63f16907cbdf53d0c149fb18f2d16e763563bc99ac05887.png","htmlSource":"pagesource430352564096056972.html","timeStamp":1707220163604,"screenshotName":"3fb8b31db7c21753f63f16907cbdf53d0c149fb18f2d16e763563bc99ac05887.png"},{"screenshot":"368c8c23959dd4cf12657a9c1f1ee9db94c923e15a2001fe5d8e88f3ebf2168b.png","timeStamp":1707220163860,"screenshotName":"368c8c23959dd4cf12657a9c1f1ee9db94c923e15a2001fe5d8e88f3ebf2168b.png"}],"result":"SUCCESS","precondition":false,"level":3},{"number":38,"description":"admin enters \u0027correo20240206064819@gmail.com\u0027 into INPUT EMAIL","duration":482,"startTime":"2024-02-06T06:49:23.868579400-05:00[America/Lima]","screenshots":[{"screenshot":"368c8c23959dd4cf12657a9c1f1ee9db94c923e15a2001fe5d8e88f3ebf2168b.png","htmlSource":"pagesource14297290525147379928.html","timeStamp":1707220163931,"screenshotName":"368c8c23959dd4cf12657a9c1f1ee9db94c923e15a2001fe5d8e88f3ebf2168b.png"},{"screenshot":"c8bcfbb0158729c02b3ca19acb0b7dea71fcdabc6bdfb1b87dd5e0ef482b4bf2.png","timeStamp":1707220164351,"screenshotName":"c8bcfbb0158729c02b3ca19acb0b7dea71fcdabc6bdfb1b87dd5e0ef482b4bf2.png"}],"result":"SUCCESS","precondition":false,"level":3},{"number":39,"description":"admin clicks on BUTTON TO SEND CLIENT TO EVALUATE","duration":1665,"startTime":"2024-02-06T06:49:24.360101300-05:00[America/Lima]","screenshots":[{"screenshot":"c8bcfbb0158729c02b3ca19acb0b7dea71fcdabc6bdfb1b87dd5e0ef482b4bf2.png","htmlSource":"pagesource15649238015459670603.html","timeStamp":1707220164421,"screenshotName":"c8bcfbb0158729c02b3ca19acb0b7dea71fcdabc6bdfb1b87dd5e0ef482b4bf2.png"},{"screenshot":"bf4965fdc919e796e088494d2c90d5137455d7f35d8fc075690b9b9ba6b9174c.png","timeStamp":1707220166025,"screenshotName":"bf4965fdc919e796e088494d2c90d5137455d7f35d8fc075690b9b9ba6b9174c.png"}],"result":"SUCCESS","precondition":false,"level":3},{"number":40,"description":"admin clicks on BUTTON PREAPROVED OK","duration":24702,"startTime":"2024-02-06T06:49:26.036176700-05:00[America/Lima]","screenshots":[{"screenshot":"bf4965fdc919e796e088494d2c90d5137455d7f35d8fc075690b9b9ba6b9174c.png","htmlSource":"pagesource6698036256117504411.html","timeStamp":1707220166085,"screenshotName":"bf4965fdc919e796e088494d2c90d5137455d7f35d8fc075690b9b9ba6b9174c.png"},{"screenshot":"c1ccd10f1a1d63809f3cfeb0c8e06be08ebd4a0bafb4abd62f80be9886415a33.png","timeStamp":1707220190738,"screenshotName":"c1ccd10f1a1d63809f3cfeb0c8e06be08ebd4a0bafb4abd62f80be9886415a33.png"}],"result":"SUCCESS","precondition":false,"level":3}]},{"number":41,"description":"Admin pre qualify personal info","duration":5619,"startTime":"2024-02-06T06:49:50.768225300-05:00[America/Lima]","screenshots":[{"screenshot":"c1ccd10f1a1d63809f3cfeb0c8e06be08ebd4a0bafb4abd62f80be9886415a33.png","htmlSource":"pagesource17571339354765271320.html","timeStamp":1707220190829,"screenshotName":"c1ccd10f1a1d63809f3cfeb0c8e06be08ebd4a0bafb4abd62f80be9886415a33.png"},{"screenshot":"702fd5e270d8dfc429b06685fb8f259a871ab7ad8d49b3e9e15299fbe52986a4.png","timeStamp":1707220196387,"screenshotName":"702fd5e270d8dfc429b06685fb8f259a871ab7ad8d49b3e9e15299fbe52986a4.png"}],"result":"SUCCESS","precondition":false,"level":2,"children":[{"number":42,"description":"admin clicks on DROPDOWN TO SELECT MARRIED STATUS FROM THE CUSTOMER","duration":1886,"startTime":"2024-02-06T06:49:51.843786200-05:00[America/Lima]","screenshots":[{"screenshot":"cccfff6f299dda8d895e57a60a15caeac14fe0dfa9e9064925c4dbfcf9863bcf.png","htmlSource":"pagesource16400423635028583902.html","timeStamp":1707220192016,"screenshotName":"cccfff6f299dda8d895e57a60a15caeac14fe0dfa9e9064925c4dbfcf9863bcf.png"},{"screenshot":"53a431b83a972bf6c1732c1fb249f90d8f32f2e82e521c4476f53f9697a8110b.png","timeStamp":1707220193730,"screenshotName":"53a431b83a972bf6c1732c1fb249f90d8f32f2e82e521c4476f53f9697a8110b.png"}],"result":"SUCCESS","precondition":false,"level":3},{"number":43,"description":"admin clicks on DROPDOWN TO SELECT COUNTRY OF BIRTH","duration":485,"startTime":"2024-02-06T06:49:53.846488500-05:00[America/Lima]","screenshots":[{"screenshot":"2fa82913be53b99b4af26c8bab24043fe3830d881336bd5b98373b8f458856ed.png","htmlSource":"pagesource2616277458562740860.html","timeStamp":1707220194045,"screenshotName":"2fa82913be53b99b4af26c8bab24043fe3830d881336bd5b98373b8f458856ed.png"},{"screenshot":"53a0efca37730cd87783067cf5337301f8102903af0a92931632bf6541ccae8b.png","timeStamp":1707220194331,"screenshotName":"53a0efca37730cd87783067cf5337301f8102903af0a92931632bf6541ccae8b.png"}],"result":"SUCCESS","precondition":false,"level":3},{"number":44,"description":"admin enters \u00273\u0027 into iNPUTS TO ENTER THE NUMBER OF DEPENDS FROM THE CUSTOMER","duration":439,"startTime":"2024-02-06T06:49:54.429992-05:00[America/Lima]","screenshots":[{"screenshot":"9e2a0ae05d6d1a01ad3cb8a07bd38c3d4266ced66ff5a1b7701e36c03d05390b.png","htmlSource":"pagesource9306309661820809798.html","timeStamp":1707220194633,"screenshotName":"9e2a0ae05d6d1a01ad3cb8a07bd38c3d4266ced66ff5a1b7701e36c03d05390b.png"},{"screenshot":"ab47884acdd3c5a90981cb617db269e42600b784b3948c737ca8b2b5ec7441d3.png","timeStamp":1707220194869,"screenshotName":"ab47884acdd3c5a90981cb617db269e42600b784b3948c737ca8b2b5ec7441d3.png"}],"result":"SUCCESS","precondition":false,"level":3},{"number":45,"description":"admin clicks on DROPDOWN TO SELECT THE PAYMENT FREQUENCY FROM THE CUSTOMER","duration":304,"startTime":"2024-02-06T06:49:54.875630-05:00[America/Lima]","screenshots":[{"screenshot":"ab47884acdd3c5a90981cb617db269e42600b784b3948c737ca8b2b5ec7441d3.png","htmlSource":"pagesource6383128739646344627.html","timeStamp":1707220194930,"screenshotName":"ab47884acdd3c5a90981cb617db269e42600b784b3948c737ca8b2b5ec7441d3.png"},{"screenshot":"21cb3b9f5704db90fb57defa3e1253664d4c8d5d4951f960ace198050dd874ec.png","timeStamp":1707220195178,"screenshotName":"21cb3b9f5704db90fb57defa3e1253664d4c8d5d4951f960ace198050dd874ec.png"}],"result":"SUCCESS","precondition":false,"level":3},{"number":46,"description":"admin enters \u00272000\u0027 into INPUT TO ENTER THE PAYMENT INCOMING EVERY MONTH","duration":471,"startTime":"2024-02-06T06:49:55.276436200-05:00[America/Lima]","screenshots":[{"screenshot":"1518784c1e1fb299a0905f3b3a8c5e19f44f7cfb9e412ee5a146e2fe67428a21.png","htmlSource":"pagesource10241558642312001692.html","timeStamp":1707220195428,"screenshotName":"1518784c1e1fb299a0905f3b3a8c5e19f44f7cfb9e412ee5a146e2fe67428a21.png"},{"screenshot":"200e1acbdb44f09df3d8a2985475ca0a4c61a0246d1f62ad5e4fcf57760deae6.png","timeStamp":1707220195748,"screenshotName":"200e1acbdb44f09df3d8a2985475ca0a4c61a0246d1f62ad5e4fcf57760deae6.png"}],"result":"SUCCESS","precondition":false,"level":3},{"number":47,"description":"admin clicks on BUTTON SAVE PERSONAL INFO","duration":278,"startTime":"2024-02-06T06:49:55.753890500-05:00[America/Lima]","screenshots":[{"screenshot":"200e1acbdb44f09df3d8a2985475ca0a4c61a0246d1f62ad5e4fcf57760deae6.png","htmlSource":"pagesource8366765659123585630.html","timeStamp":1707220195801,"screenshotName":"200e1acbdb44f09df3d8a2985475ca0a4c61a0246d1f62ad5e4fcf57760deae6.png"},{"screenshot":"5f8b2d0a60a12ee3b65d21df8c2c27318b0c4301109e4ec46fa2962ba217c877.png","timeStamp":1707220196031,"screenshotName":"5f8b2d0a60a12ee3b65d21df8c2c27318b0c4301109e4ec46fa2962ba217c877.png"}],"result":"SUCCESS","precondition":false,"level":3},{"number":48,"description":"admin clicks on Confirm the incoming amount","duration":315,"startTime":"2024-02-06T06:49:56.043338300-05:00[America/Lima]","screenshots":[{"screenshot":"5f8b2d0a60a12ee3b65d21df8c2c27318b0c4301109e4ec46fa2962ba217c877.png","htmlSource":"pagesource12183276535720537285.html","timeStamp":1707220196097,"screenshotName":"5f8b2d0a60a12ee3b65d21df8c2c27318b0c4301109e4ec46fa2962ba217c877.png"},{"screenshot":"702fd5e270d8dfc429b06685fb8f259a871ab7ad8d49b3e9e15299fbe52986a4.png","timeStamp":1707220196359,"screenshotName":"702fd5e270d8dfc429b06685fb8f259a871ab7ad8d49b3e9e15299fbe52986a4.png"}],"result":"SUCCESS","precondition":false,"level":3}]},{"number":49,"description":"Admin pre qualify work info","duration":15940,"startTime":"2024-02-06T06:49:56.402142400-05:00[America/Lima]","screenshots":[{"screenshot":"b7cb1f38e93631b3695733abff1d21fe6ec2be8c5e63555e2ab1fae75c565b88.png","htmlSource":"pagesource10605477378238108923.html","timeStamp":1707220197080,"screenshotName":"b7cb1f38e93631b3695733abff1d21fe6ec2be8c5e63555e2ab1fae75c565b88.png"},{"screenshot":"d7d8f406e4cc15c4567ebfb664686c3a8bf7fb86e62ee5e3bf915181031e24d2.png","timeStamp":1707220212342,"screenshotName":"d7d8f406e4cc15c4567ebfb664686c3a8bf7fb86e62ee5e3bf915181031e24d2.png"}],"result":"SUCCESS","precondition":false,"level":2,"children":[{"number":50,"description":"admin clicks on INPUT FOR WORK MAIN ECONOMIC ACTIVITY","duration":987,"startTime":"2024-02-06T06:49:58.103140-05:00[America/Lima]","screenshots":[{"screenshot":"b7cb1f38e93631b3695733abff1d21fe6ec2be8c5e63555e2ab1fae75c565b88.png","htmlSource":"pagesource10630286095741924379.html","timeStamp":1707220198806,"screenshotName":"b7cb1f38e93631b3695733abff1d21fe6ec2be8c5e63555e2ab1fae75c565b88.png"},{"screenshot":"9db9cdebad4ef93a735d4eb31e0a029e99e68a0bfef320811482c1fe48707dba.png","timeStamp":1707220199091,"screenshotName":"9db9cdebad4ef93a735d4eb31e0a029e99e68a0bfef320811482c1fe48707dba.png"}],"result":"SUCCESS","precondition":false,"level":3},{"number":51,"description":"admin clicks on DROPDOWN TO SELECT THE MAIN OCCUPATION","duration":379,"startTime":"2024-02-06T06:50:00.193119-05:00[America/Lima]","screenshots":[{"screenshot":"bd6aeb5e552385dcf73b7740d1ba825719ef5eb4bb841d9b65a6b16a56597bfc.png","htmlSource":"pagesource8463469556908316273.html","timeStamp":1707220200314,"screenshotName":"bd6aeb5e552385dcf73b7740d1ba825719ef5eb4bb841d9b65a6b16a56597bfc.png"},{"screenshot":"2550887ae5d23ef75fb33107ecefa5494d4dbc0c4b894009b9fc4cac8b3ff6e3.png","timeStamp":1707220200572,"screenshotName":"2550887ae5d23ef75fb33107ecefa5494d4dbc0c4b894009b9fc4cac8b3ff6e3.png"}],"result":"SUCCESS","precondition":false,"level":3},{"number":52,"description":"admin enters \u0027UNICOMER SAC\u0027 into INPUT FOR EMPLOYER NAME","duration":465,"startTime":"2024-02-06T06:50:00.678287300-05:00[America/Lima]","screenshots":[{"screenshot":"e8ca05b60f53763f0b69c1eb3bc94fe48cddd7e67cb025c3894ebc3f0162443c.png","htmlSource":"pagesource5394281882338371363.html","timeStamp":1707220200844,"screenshotName":"e8ca05b60f53763f0b69c1eb3bc94fe48cddd7e67cb025c3894ebc3f0162443c.png"},{"screenshot":"d0fc577441dfc54d9841bcb6a0c535a4294fe58b299a1ab64b12cbfc69300a3f.png","timeStamp":1707220201143,"screenshotName":"d0fc577441dfc54d9841bcb6a0c535a4294fe58b299a1ab64b12cbfc69300a3f.png"}],"result":"SUCCESS","precondition":false,"level":3},{"number":53,"description":"admin clicks on BUTTON EMPLOYMENT START DATE","duration":973,"startTime":"2024-02-06T06:50:02.156903700-05:00[America/Lima]","screenshots":[{"screenshot":"6e3c254b6b64141a50cd2f3fd576f8980e044d3512d9f708475153135b72eca4.png","htmlSource":"pagesource14831630486207692288.html","timeStamp":1707220202854,"screenshotName":"6e3c254b6b64141a50cd2f3fd576f8980e044d3512d9f708475153135b72eca4.png"},{"screenshot":"33a55b3171f960f3c3eb1cfa19173934f6f3ddfae15654b3996a5fe92055907c.png","timeStamp":1707220203130,"screenshotName":"33a55b3171f960f3c3eb1cfa19173934f6f3ddfae15654b3996a5fe92055907c.png"}],"result":"SUCCESS","precondition":false,"level":3},{"number":54,"description":"admin clicks on BUTTON BACK YEARS ","duration":306,"startTime":"2024-02-06T06:50:03.136056600-05:00[America/Lima]","screenshots":[{"screenshot":"33a55b3171f960f3c3eb1cfa19173934f6f3ddfae15654b3996a5fe92055907c.png","htmlSource":"pagesource3375840140762293647.html","timeStamp":1707220203195,"screenshotName":"33a55b3171f960f3c3eb1cfa19173934f6f3ddfae15654b3996a5fe92055907c.png"},{"screenshot":"371b914653da77dddc25755dd26b818938a58826e004808fcd0ad57a38d87dc2.png","timeStamp":1707220203442,"screenshotName":"371b914653da77dddc25755dd26b818938a58826e004808fcd0ad57a38d87dc2.png"}],"result":"SUCCESS","precondition":false,"level":3},{"number":55,"description":"admin clicks on DROPDOWN TO SELECT PARISH OF WORK","duration":385,"startTime":"2024-02-06T06:50:05.119811900-05:00[America/Lima]","screenshots":[{"screenshot":"1febc40f9df4191188dd8dc2d65102b54b9f0da2e1c2f66b809ae92db93df84f.png","htmlSource":"pagesource18425344394360419443.html","timeStamp":1707220205264,"screenshotName":"1febc40f9df4191188dd8dc2d65102b54b9f0da2e1c2f66b809ae92db93df84f.png"},{"screenshot":"03add4a958e8b1a218d8efd2c4085ddaa6e1a85c9427fce532d4f3a925f4ceef.png","timeStamp":1707220205505,"screenshotName":"03add4a958e8b1a218d8efd2c4085ddaa6e1a85c9427fce532d4f3a925f4ceef.png"}],"result":"SUCCESS","precondition":false,"level":3},{"number":56,"description":"admin clicks on DROPDOWN TO SELECT DISTRICT OF WORK","duration":794,"startTime":"2024-02-06T06:50:05.601089500-05:00[America/Lima]","screenshots":[{"screenshot":"899bd881bd919377e249fac8a29b9fdcdf2a7e5f7340fd6dc7308c27742e53dd.png","htmlSource":"pagesource16066587879844211060.html","timeStamp":1707220205781,"screenshotName":"899bd881bd919377e249fac8a29b9fdcdf2a7e5f7340fd6dc7308c27742e53dd.png"},{"screenshot":"c3dcd5cdf293af6fc0a8062187079c0840b280376a1432d5c0e29cabec41e162.png","timeStamp":1707220206395,"screenshotName":"c3dcd5cdf293af6fc0a8062187079c0840b280376a1432d5c0e29cabec41e162.png"}],"result":"SUCCESS","precondition":false,"level":3},{"number":57,"description":"admin enters \u002779-80 A SUPER ROAD\u0027 into IMPUT FOR YOUR CURRENT WORK ADDRESS","duration":510,"startTime":"2024-02-06T06:50:06.498670600-05:00[America/Lima]","screenshots":[{"screenshot":"56bf025efe5166c8f72d89de6c40b996c4a1f18f9b3f33dd3a1c373ca06175f5.png","htmlSource":"pagesource12029166081720871387.html","timeStamp":1707220206665,"screenshotName":"56bf025efe5166c8f72d89de6c40b996c4a1f18f9b3f33dd3a1c373ca06175f5.png"},{"screenshot":"32eee8831ac6a8f0be426733a1ea388b4a1903c774d786924ec005d661409f61.png","timeStamp":1707220207009,"screenshotName":"32eee8831ac6a8f0be426733a1ea388b4a1903c774d786924ec005d661409f61.png"}],"result":"SUCCESS","precondition":false,"level":3},{"number":58,"description":"admin enters \u002779 -81a Road UNITED\u0027 into INPUT WORK REFERENCE","duration":369,"startTime":"2024-02-06T06:50:07.016005200-05:00[America/Lima]","screenshots":[{"screenshot":"32eee8831ac6a8f0be426733a1ea388b4a1903c774d786924ec005d661409f61.png","htmlSource":"pagesource5507250890811201622.html","timeStamp":1707220207073,"screenshotName":"32eee8831ac6a8f0be426733a1ea388b4a1903c774d786924ec005d661409f61.png"},{"screenshot":"28f93935cdae2f4f54b6093851652433c615f04dd8dabf3e6d2d3423458a0537.png","timeStamp":1707220207385,"screenshotName":"28f93935cdae2f4f54b6093851652433c615f04dd8dabf3e6d2d3423458a0537.png"}],"result":"SUCCESS","precondition":false,"level":3},{"number":59,"description":"admin clicks on DROPDOWN TO SELECT AREA CODE","duration":1663,"startTime":"2024-02-06T06:50:07.393442900-05:00[America/Lima]","screenshots":[{"screenshot":"28f93935cdae2f4f54b6093851652433c615f04dd8dabf3e6d2d3423458a0537.png","htmlSource":"pagesource12761979743502199680.html","timeStamp":1707220207448,"screenshotName":"28f93935cdae2f4f54b6093851652433c615f04dd8dabf3e6d2d3423458a0537.png"},{"screenshot":"d7c2a40afb749db12fe95ff403563b5fbff0d6d95919124fcbb4d639df125396.png","timeStamp":1707220209056,"screenshotName":"d7c2a40afb749db12fe95ff403563b5fbff0d6d95919124fcbb4d639df125396.png"}],"result":"SUCCESS","precondition":false,"level":3},{"number":60,"description":"admin enters \u00271598788\u0027 into INPUT FOR MOBILE WORK NUMBER","duration":417,"startTime":"2024-02-06T06:50:09.164341800-05:00[America/Lima]","screenshots":[{"screenshot":"bd130fc91bd1ab902e09367557a46a8580e734b3b086e6c9038f675d96afda89.png","htmlSource":"pagesource11768872496656842420.html","timeStamp":1707220209322,"screenshotName":"bd130fc91bd1ab902e09367557a46a8580e734b3b086e6c9038f675d96afda89.png"},{"screenshot":"413c62ebc62c95357b7b3ff5331c20f43ce8136b70da2f1295b5e5d4ab7d31e4.png","timeStamp":1707220209581,"screenshotName":"413c62ebc62c95357b7b3ff5331c20f43ce8136b70da2f1295b5e5d4ab7d31e4.png"}],"result":"SUCCESS","precondition":false,"level":3},{"number":61,"description":"admin clicks on SAVE INFO WORK INFO","duration":1734,"startTime":"2024-02-06T06:50:10.597439200-05:00[America/Lima]","screenshots":[{"screenshot":"db240fe19f46b1b2318bf5b3b32ebacb7a7316b0fcb94decf75ae5a052ba5e18.png","htmlSource":"pagesource8515526672160401274.html","timeStamp":1707220210721,"screenshotName":"db240fe19f46b1b2318bf5b3b32ebacb7a7316b0fcb94decf75ae5a052ba5e18.png"},{"screenshot":"d7d8f406e4cc15c4567ebfb664686c3a8bf7fb86e62ee5e3bf915181031e24d2.png","timeStamp":1707220212332,"screenshotName":"d7d8f406e4cc15c4567ebfb664686c3a8bf7fb86e62ee5e3bf915181031e24d2.png"}],"result":"SUCCESS","precondition":false,"level":3}]},{"number":62,"description":"Admin pre qualify location","duration":10651,"startTime":"2024-02-06T06:50:12.352776600-05:00[America/Lima]","screenshots":[{"screenshot":"d7d8f406e4cc15c4567ebfb664686c3a8bf7fb86e62ee5e3bf915181031e24d2.png","htmlSource":"pagesource6493637324557005707.html","timeStamp":1707220212406,"screenshotName":"d7d8f406e4cc15c4567ebfb664686c3a8bf7fb86e62ee5e3bf915181031e24d2.png"},{"screenshot":"49bda2872401e17d884638ad9c46578236c16e8c06bc3067c79ff4c3d58ea382.png","timeStamp":1707220223003,"screenshotName":"49bda2872401e17d884638ad9c46578236c16e8c06bc3067c79ff4c3d58ea382.png"}],"result":"SUCCESS","precondition":false,"level":2,"children":[{"number":63,"description":"admin clicks on DROPDOWN TO SELECT PARISH OF CUSTOMER","duration":1695,"startTime":"2024-02-06T06:50:13.436902800-05:00[America/Lima]","screenshots":[{"screenshot":"59e2741e3751ac9b7c15ccd273a6f16313ebdccec39085416aa4b0602bb19163.png","htmlSource":"pagesource13264329654521736459.html","timeStamp":1707220213566,"screenshotName":"59e2741e3751ac9b7c15ccd273a6f16313ebdccec39085416aa4b0602bb19163.png"},{"screenshot":"1a10c7acf2f9b2ddcb7b4aabea5c8b4b47b3e5993081f3fc6fc0620c019b3506.png","timeStamp":1707220215132,"screenshotName":"1a10c7acf2f9b2ddcb7b4aabea5c8b4b47b3e5993081f3fc6fc0620c019b3506.png"}],"result":"SUCCESS","precondition":false,"level":3},{"number":64,"description":"admin clicks on DROPDOWN TO SELECT DISTRICT OF CUSTOMER","duration":898,"startTime":"2024-02-06T06:50:15.226523300-05:00[America/Lima]","screenshots":[{"screenshot":"318916c6e1353a48cb81cfdde841ef8616765ea0b6dfa6fb5a4208eda4b6d7e9.png","htmlSource":"pagesource3056647296100855609.html","timeStamp":1707220215386,"screenshotName":"318916c6e1353a48cb81cfdde841ef8616765ea0b6dfa6fb5a4208eda4b6d7e9.png"},{"screenshot":"1b906e0beb936162418713d59daaf6710eec82d968d355aad37982dd5723c3a8.png","timeStamp":1707220216125,"screenshotName":"1b906e0beb936162418713d59daaf6710eec82d968d355aad37982dd5723c3a8.png"}],"result":"SUCCESS","precondition":false,"level":3},{"number":65,"description":"admin enters \u0027X5X9+QQQ, LAS VEGAS\u0027 into INPUT RESIDENCE STREET","duration":533,"startTime":"2024-02-06T06:50:16.209148-05:00[America/Lima]","screenshots":[{"screenshot":"91886a455233f2d4800a57c3a5f5ad69a54aefe06627863cabd14dff0cc2d9f7.png","htmlSource":"pagesource18437670377493626263.html","timeStamp":1707220216384,"screenshotName":"91886a455233f2d4800a57c3a5f5ad69a54aefe06627863cabd14dff0cc2d9f7.png"},{"screenshot":"bc14fe68dcc8c22c0b4642c0b627aa7f0efb45f6d34b41e0e3a81151fcc319a5.png","timeStamp":1707220216742,"screenshotName":"bc14fe68dcc8c22c0b4642c0b627aa7f0efb45f6d34b41e0e3a81151fcc319a5.png"}],"result":"SUCCESS","precondition":false,"level":3},{"number":66,"description":"admin enters \u0027What is D\u0026Bs\u0027 into INPUT TO ENTER FIRST PERSONAL REFERENCE","duration":339,"startTime":"2024-02-06T06:50:16.751206-05:00[America/Lima]","screenshots":[{"screenshot":"bc14fe68dcc8c22c0b4642c0b627aa7f0efb45f6d34b41e0e3a81151fcc319a5.png","htmlSource":"pagesource15057681282214174080.html","timeStamp":1707220216802,"screenshotName":"bc14fe68dcc8c22c0b4642c0b627aa7f0efb45f6d34b41e0e3a81151fcc319a5.png"},{"screenshot":"32691109e614b95cf2ddb303b16042e3bd3abed935f1da88ee298bed504382a3.png","timeStamp":1707220217090,"screenshotName":"32691109e614b95cf2ddb303b16042e3bd3abed935f1da88ee298bed504382a3.png"}],"result":"SUCCESS","precondition":false,"level":3},{"number":67,"description":"admin clicks on INPUT TO ENTER MONTHS AT CURRENT ADDRESS","duration":394,"startTime":"2024-02-06T06:50:18.102614600-05:00[America/Lima]","screenshots":[{"screenshot":"32691109e614b95cf2ddb303b16042e3bd3abed935f1da88ee298bed504382a3.png","htmlSource":"pagesource7825401993089116655.html","timeStamp":1707220218222,"screenshotName":"32691109e614b95cf2ddb303b16042e3bd3abed935f1da88ee298bed504382a3.png"},{"screenshot":"b6527126fb58d85b0dd4b742192108e70b126aa0865ee66f0a6dd4e7f24afaa6.png","timeStamp":1707220218497,"screenshotName":"b6527126fb58d85b0dd4b742192108e70b126aa0865ee66f0a6dd4e7f24afaa6.png"}],"result":"SUCCESS","precondition":false,"level":3},{"number":68,"description":"admin clicks on DROPDOWN TO SELECT RESIDENT STATUS OF CUSTOMER","duration":421,"startTime":"2024-02-06T06:50:18.939887900-05:00[America/Lima]","screenshots":[{"screenshot":"457038d1b1b29e4c22d97e5ebdbdc696a2190b5bc6f47089681209b75fd3488b.png","htmlSource":"pagesource10162023749003704299.html","timeStamp":1707220219118,"screenshotName":"457038d1b1b29e4c22d97e5ebdbdc696a2190b5bc6f47089681209b75fd3488b.png"},{"screenshot":"975b2ef2781336d9845ea7582e63ad93756579d6d7462795189d336c97ef75ac.png","timeStamp":1707220219361,"screenshotName":"975b2ef2781336d9845ea7582e63ad93756579d6d7462795189d336c97ef75ac.png"}],"result":"SUCCESS","precondition":false,"level":3},{"number":69,"description":"admin clicks on CONFIRM SAVE LOCATION DATA","duration":408,"startTime":"2024-02-06T06:50:21.445611500-05:00[America/Lima]","screenshots":[{"screenshot":"d1a0df966c06f04d9531cf358942cf6050d7803419daa423b88b8b5edfa4fa28.png","htmlSource":"pagesource9158755563134858817.html","timeStamp":1707220221621,"screenshotName":"d1a0df966c06f04d9531cf358942cf6050d7803419daa423b88b8b5edfa4fa28.png"},{"screenshot":"89baf9d83a327409951d298f16b10f4deec4c76d1a51a1de94a0ae0a51bc2a99.png","timeStamp":1707220221854,"screenshotName":"89baf9d83a327409951d298f16b10f4deec4c76d1a51a1de94a0ae0a51bc2a99.png"}],"result":"SUCCESS","precondition":false,"level":3}]},{"number":70,"description":"Admin pre qualify references","duration":17792,"startTime":"2024-02-06T06:50:23.010340300-05:00[America/Lima]","screenshots":[{"screenshot":"49bda2872401e17d884638ad9c46578236c16e8c06bc3067c79ff4c3d58ea382.png","htmlSource":"pagesource1926398970398623367.html","timeStamp":1707220223069,"screenshotName":"49bda2872401e17d884638ad9c46578236c16e8c06bc3067c79ff4c3d58ea382.png"},{"screenshot":"b6a5317bb9a35817bf821b7c0ee151faa30d5a6f99942ef405b35c5520b0d9af.png","timeStamp":1707220240802,"screenshotName":"b6a5317bb9a35817bf821b7c0ee151faa30d5a6f99942ef405b35c5520b0d9af.png"}],"result":"SUCCESS","precondition":false,"level":2,"children":[{"number":71,"description":"admin enters \u0027HERNAN PAREDES\u0027 into INPUT TO ENTER FIRST PERSONAL REFERENCE","duration":568,"startTime":"2024-02-06T06:50:24.082014600-05:00[America/Lima]","screenshots":[{"screenshot":"49bda2872401e17d884638ad9c46578236c16e8c06bc3067c79ff4c3d58ea382.png","htmlSource":"pagesource2380153520940039785.html","timeStamp":1707220224252,"screenshotName":"49bda2872401e17d884638ad9c46578236c16e8c06bc3067c79ff4c3d58ea382.png"},{"screenshot":"9f7f213db24e63656b279a70605e146000327cb98b4279cc8bc8ff8ec89c4a05.png","timeStamp":1707220224650,"screenshotName":"9f7f213db24e63656b279a70605e146000327cb98b4279cc8bc8ff8ec89c4a05.png"}],"result":"SUCCESS","precondition":false,"level":3},{"number":72,"description":"admin clicks on DROPDOWN TO SELECT RELATIONSHIP","duration":312,"startTime":"2024-02-06T06:50:24.654918500-05:00[America/Lima]","screenshots":[{"screenshot":"9f7f213db24e63656b279a70605e146000327cb98b4279cc8bc8ff8ec89c4a05.png","htmlSource":"pagesource253912462390954836.html","timeStamp":1707220224721,"screenshotName":"9f7f213db24e63656b279a70605e146000327cb98b4279cc8bc8ff8ec89c4a05.png"},{"screenshot":"8712847c8952fa4755e7c409204ad834d580187055ba29eba0e30486b4839d2f.png","timeStamp":1707220224966,"screenshotName":"8712847c8952fa4755e7c409204ad834d580187055ba29eba0e30486b4839d2f.png"}],"result":"SUCCESS","precondition":false,"level":3},{"number":73,"description":"admin clicks on DROPDOWN TO SELECT RELATIONSHIP","duration":404,"startTime":"2024-02-06T06:50:25.062333500-05:00[America/Lima]","screenshots":[{"screenshot":"de43663c9548f3d1bfe878bf5ac433adccd440f37f669d3fe4ebd558c851d87e.png","htmlSource":"pagesource9021566845772749290.html","timeStamp":1707220225244,"screenshotName":"de43663c9548f3d1bfe878bf5ac433adccd440f37f669d3fe4ebd558c851d87e.png"},{"screenshot":"7f12ef7067a37a1383eb6c97525b2f546d4d22fccf04e13725f728a24b0cc946.png","timeStamp":1707220225466,"screenshotName":"7f12ef7067a37a1383eb6c97525b2f546d4d22fccf04e13725f728a24b0cc946.png"}],"result":"SUCCESS","precondition":false,"level":3},{"number":74,"description":"admin clicks on DROPDOWN TO SELECT AREA CODE","duration":950,"startTime":"2024-02-06T06:50:26.560449900-05:00[America/Lima]","screenshots":[{"screenshot":"63ab89ad9984172776cb4bf3d5f000532989df85bf72a83541aafd64dda34ec1.png","htmlSource":"pagesource10589266485139554811.html","timeStamp":1707220227255,"screenshotName":"63ab89ad9984172776cb4bf3d5f000532989df85bf72a83541aafd64dda34ec1.png"},{"screenshot":"f5d60d8f489b55a66f9f05347f62873266faa3a75064f9c4b0f329c26f9a8538.png","timeStamp":1707220227511,"screenshotName":"f5d60d8f489b55a66f9f05347f62873266faa3a75064f9c4b0f329c26f9a8538.png"}],"result":"SUCCESS","precondition":false,"level":3},{"number":75,"description":"admin enters \u00271593645\u0027 into INPUT TO ENTER FIRST PERSONAL REFERENCE NUMBER","duration":930,"startTime":"2024-02-06T06:50:28.647975-05:00[America/Lima]","screenshots":[{"screenshot":"24e10c123a47352635c7b2809cac2db025cd49ce7c8ec3e6c3f0f3f70fe803d8.png","htmlSource":"pagesource5224279283656266697.html","timeStamp":1707220229304,"screenshotName":"24e10c123a47352635c7b2809cac2db025cd49ce7c8ec3e6c3f0f3f70fe803d8.png"},{"screenshot":"6b403a2833bf0205ccd69dda191e5b2d5b26d8cd0e044b21f37e0e5033c431a2.png","timeStamp":1707220229578,"screenshotName":"6b403a2833bf0205ccd69dda191e5b2d5b26d8cd0e044b21f37e0e5033c431a2.png"}],"result":"SUCCESS","precondition":false,"level":3},{"number":76,"description":"admin enters \u0027JULIAN ALVAREZ\u0027 into INPUT TO ENTER SECOND PERSONAL REFERENCE","duration":495,"startTime":"2024-02-06T06:50:31.596632900-05:00[America/Lima]","screenshots":[{"screenshot":"6b403a2833bf0205ccd69dda191e5b2d5b26d8cd0e044b21f37e0e5033c431a2.png","htmlSource":"pagesource13916075927136368529.html","timeStamp":1707220231752,"screenshotName":"6b403a2833bf0205ccd69dda191e5b2d5b26d8cd0e044b21f37e0e5033c431a2.png"},{"screenshot":"b789130bb963f8383ec56ab79f2ea2058c1254b3f5f19035d2b327dafffbdf48.png","timeStamp":1707220232092,"screenshotName":"b789130bb963f8383ec56ab79f2ea2058c1254b3f5f19035d2b327dafffbdf48.png"}],"result":"SUCCESS","precondition":false,"level":3},{"number":77,"description":"admin clicks on DROPDOWN TO SELECT RELATIONSHIP SECOND REF","duration":278,"startTime":"2024-02-06T06:50:32.097571500-05:00[America/Lima]","screenshots":[{"screenshot":"b789130bb963f8383ec56ab79f2ea2058c1254b3f5f19035d2b327dafffbdf48.png","htmlSource":"pagesource4545908803188800845.html","timeStamp":1707220232149,"screenshotName":"b789130bb963f8383ec56ab79f2ea2058c1254b3f5f19035d2b327dafffbdf48.png"},{"screenshot":"b3f63dbcb5e1bb94c1b8304632f9cd6cd50e6db0fb1ef7fc85285bb592c581e8.png","timeStamp":1707220232376,"screenshotName":"b3f63dbcb5e1bb94c1b8304632f9cd6cd50e6db0fb1ef7fc85285bb592c581e8.png"}],"result":"SUCCESS","precondition":false,"level":3},{"number":78,"description":"admin clicks on DROPDOWN TO SELECT RELATIONSHIP SECOND REF","duration":901,"startTime":"2024-02-06T06:50:33.473391300-05:00[America/Lima]","screenshots":[{"screenshot":"965047262365890bf074a7c149e9619e17734707db93a1d63ff73de5a12b17e6.png","htmlSource":"pagesource15198269257504475025.html","timeStamp":1707220234136,"screenshotName":"965047262365890bf074a7c149e9619e17734707db93a1d63ff73de5a12b17e6.png"},{"screenshot":"d6a79d7691c94fad47f921aac1969d49847f9da1706d99961cf29da9761e4278.png","timeStamp":1707220234374,"screenshotName":"d6a79d7691c94fad47f921aac1969d49847f9da1706d99961cf29da9761e4278.png"}],"result":"SUCCESS","precondition":false,"level":3},{"number":79,"description":"admin clicks on DROPDOWN TO SELECT AREA CODE","duration":1898,"startTime":"2024-02-06T06:50:34.459224600-05:00[America/Lima]","screenshots":[{"screenshot":"37efffa49b5a5faf60d5991143bf9477058d313b0106665789df43a685f9a136.png","htmlSource":"pagesource1434425002087463354.html","timeStamp":1707220234625,"screenshotName":"37efffa49b5a5faf60d5991143bf9477058d313b0106665789df43a685f9a136.png"},{"screenshot":"92552cd11abae22be144ccf20d39666f57696b819d291348c597b474ff2e6041.png","timeStamp":1707220236357,"screenshotName":"92552cd11abae22be144ccf20d39666f57696b819d291348c597b474ff2e6041.png"}],"result":"SUCCESS","precondition":false,"level":3},{"number":80,"description":"admin enters \u00273697415\u0027 into INPUT TO ENTER FIRST PERSONAL REFERENCE NUMBER","duration":446,"startTime":"2024-02-06T06:50:36.445768900-05:00[America/Lima]","screenshots":[{"screenshot":"5b4c376d492451f9f930af12e70dcb66b342b09f2b4ff32a68f32dc55918bbb1.png","htmlSource":"pagesource15483497306172526126.html","timeStamp":1707220236650,"screenshotName":"5b4c376d492451f9f930af12e70dcb66b342b09f2b4ff32a68f32dc55918bbb1.png"},{"screenshot":"4905fbe2d6d06d7c96ab98e85ed85330e896b16b995ad0cf9cbbd581c821d9c7.png","timeStamp":1707220236892,"screenshotName":"4905fbe2d6d06d7c96ab98e85ed85330e896b16b995ad0cf9cbbd581c821d9c7.png"}],"result":"SUCCESS","precondition":false,"level":3},{"number":81,"description":"admin clicks on CONFIRM FORM AND GO TO THE NEXT STEPS","duration":1765,"startTime":"2024-02-06T06:50:37.913965500-05:00[America/Lima]","screenshots":[{"screenshot":"12f01b41778627d8d226873f5519335c1352a998d348ffdc3258c4ffc5f5b310.png","htmlSource":"pagesource7830229482924533912.html","timeStamp":1707220238033,"screenshotName":"12f01b41778627d8d226873f5519335c1352a998d348ffdc3258c4ffc5f5b310.png"},{"screenshot":"a41d902a6dd0bb246123d969902dd1e2fc7f304c74d84729590885917d478afd.png","timeStamp":1707220239679,"screenshotName":"a41d902a6dd0bb246123d969902dd1e2fc7f304c74d84729590885917d478afd.png"}],"result":"SUCCESS","precondition":false,"level":3}]},{"number":82,"description":"Admin pre qualify upload documents","duration":51353,"startTime":"2024-02-06T06:50:40.808979200-05:00[America/Lima]","screenshots":[{"screenshot":"b6a5317bb9a35817bf821b7c0ee151faa30d5a6f99942ef405b35c5520b0d9af.png","htmlSource":"pagesource17951991988592767455.html","timeStamp":1707220240856,"screenshotName":"b6a5317bb9a35817bf821b7c0ee151faa30d5a6f99942ef405b35c5520b0d9af.png"},{"screenshot":"1733adfd3bf64d98c1ab393393c29c69955413842509a1ce9085eab8f43a8954.png","timeStamp":1707220292162,"screenshotName":"1733adfd3bf64d98c1ab393393c29c69955413842509a1ce9085eab8f43a8954.png"}],"result":"SUCCESS","precondition":false,"level":2,"children":[{"number":83,"description":"admin clicks on ICON BOX TO UPLOAD DOCUMENTS","duration":926,"startTime":"2024-02-06T06:50:41.867155800-05:00[America/Lima]","screenshots":[{"screenshot":"b6a5317bb9a35817bf821b7c0ee151faa30d5a6f99942ef405b35c5520b0d9af.png","htmlSource":"pagesource3867457757902373521.html","timeStamp":1707220242535,"screenshotName":"b6a5317bb9a35817bf821b7c0ee151faa30d5a6f99942ef405b35c5520b0d9af.png"},{"screenshot":"c9c890bd5a594e8489f9cd310097438fb9ebb70b362f48077bfbeb741906f83d.png","timeStamp":1707220242793,"screenshotName":"c9c890bd5a594e8489f9cd310097438fb9ebb70b362f48077bfbeb741906f83d.png"}],"result":"SUCCESS","precondition":false,"level":3},{"number":84,"description":"admin enters \u0027D:\\FRACTAL\\UNICOMER\\AUTO\\ecosystem-regression/src/test/resources/files/dni.PNG\u0027 into INPUT DOCUMENT FILE","duration":323,"startTime":"2024-02-06T06:50:43.003414300-05:00[America/Lima]","screenshots":[{"screenshot":"4ddbb58e2314155660344055271db7e0b2f96380484dc23cb43774b629a48b0c.png","htmlSource":"pagesource2383237593740099541.html","timeStamp":1707220243178,"screenshotName":"4ddbb58e2314155660344055271db7e0b2f96380484dc23cb43774b629a48b0c.png"},{"screenshot":"fb9e979bef29f07f679ab8b6a64d91951c0702c9eca40d7ed918cd48896639bd.png","timeStamp":1707220243326,"screenshotName":"fb9e979bef29f07f679ab8b6a64d91951c0702c9eca40d7ed918cd48896639bd.png"}],"result":"SUCCESS","precondition":false,"level":3},{"number":85,"description":"admin clicks on ICON BOX TO UPLOAD DOCUMENTS","duration":896,"startTime":"2024-02-06T06:50:51.532676200-05:00[America/Lima]","screenshots":[{"screenshot":"917e16044b907aac3039e7b9c52fa17e027136eae7b9b1b010305e6686e571a8.png","htmlSource":"pagesource11494179981973458975.html","timeStamp":1707220252188,"screenshotName":"917e16044b907aac3039e7b9c52fa17e027136eae7b9b1b010305e6686e571a8.png"},{"screenshot":"9525ea6a3c3fe80c048b2f3d8425ca31c66b5b9bcdcb3ed285975141d560d8bc.png","timeStamp":1707220252428,"screenshotName":"9525ea6a3c3fe80c048b2f3d8425ca31c66b5b9bcdcb3ed285975141d560d8bc.png"}],"result":"SUCCESS","precondition":false,"level":3},{"number":86,"description":"admin enters \u0027D:\\FRACTAL\\UNICOMER\\AUTO\\ecosystem-regression/src/test/resources/files/dni.PNG\u0027 into INPUT DOCUMENT FILE","duration":204,"startTime":"2024-02-06T06:50:52.440970400-05:00[America/Lima]","screenshots":[{"screenshot":"9525ea6a3c3fe80c048b2f3d8425ca31c66b5b9bcdcb3ed285975141d560d8bc.png","htmlSource":"pagesource4862165596483193918.html","timeStamp":1707220252492,"screenshotName":"9525ea6a3c3fe80c048b2f3d8425ca31c66b5b9bcdcb3ed285975141d560d8bc.png"},{"screenshot":"30ce429cd928536fdef66bb9042e819e2a51b88b43eb2a6ed881edec6776e893.png","timeStamp":1707220252645,"screenshotName":"30ce429cd928536fdef66bb9042e819e2a51b88b43eb2a6ed881edec6776e893.png"}],"result":"SUCCESS","precondition":false,"level":3},{"number":87,"description":"admin clicks on ICON BOX TO UPLOAD DOCUMENTS","duration":894,"startTime":"2024-02-06T06:51:00.817788600-05:00[America/Lima]","screenshots":[{"screenshot":"6753ef3da191e5e93554bb0840063df6a694f6891282d4801dfd36f0a9e1011d.png","htmlSource":"pagesource9450737553135395204.html","timeStamp":1707220261488,"screenshotName":"6753ef3da191e5e93554bb0840063df6a694f6891282d4801dfd36f0a9e1011d.png"},{"screenshot":"a922f220e48d517a750370c8fec82069c87960d379f7740a9543af05b73bef2f.png","timeStamp":1707220261712,"screenshotName":"a922f220e48d517a750370c8fec82069c87960d379f7740a9543af05b73bef2f.png"}],"result":"SUCCESS","precondition":false,"level":3},{"number":88,"description":"admin enters \u0027D:\\FRACTAL\\UNICOMER\\AUTO\\ecosystem-regression/src/test/resources/files/dni.PNG\u0027 into INPUT DOCUMENT FILE","duration":199,"startTime":"2024-02-06T06:51:01.718639100-05:00[America/Lima]","screenshots":[{"screenshot":"a922f220e48d517a750370c8fec82069c87960d379f7740a9543af05b73bef2f.png","htmlSource":"pagesource16583087245831639106.html","timeStamp":1707220261769,"screenshotName":"a922f220e48d517a750370c8fec82069c87960d379f7740a9543af05b73bef2f.png"},{"screenshot":"af69630b9870d5318a86d3d4fe748f52c36d25e071c98c35a45873b0dff3b766.png","timeStamp":1707220261918,"screenshotName":"af69630b9870d5318a86d3d4fe748f52c36d25e071c98c35a45873b0dff3b766.png"}],"result":"SUCCESS","precondition":false,"level":3},{"number":89,"description":"admin clicks on ICON BOX TO UPLOAD DOCUMENTS","duration":1415,"startTime":"2024-02-06T06:51:10.070424900-05:00[America/Lima]","screenshots":[{"screenshot":"93b246f70527a82614cca6a89c08a35eb76a134249ff80ff33ef1129895f1c9d.png","htmlSource":"pagesource5038194776154594887.html","timeStamp":1707220270747,"screenshotName":"93b246f70527a82614cca6a89c08a35eb76a134249ff80ff33ef1129895f1c9d.png"},{"screenshot":"4dd6f6bf88b52b5bd75e0a163001d0cd0b78d41f22257a97ea15347437ac6750.png","timeStamp":1707220271486,"screenshotName":"4dd6f6bf88b52b5bd75e0a163001d0cd0b78d41f22257a97ea15347437ac6750.png"}],"result":"SUCCESS","precondition":false,"level":3},{"number":90,"description":"admin enters \u0027D:\\FRACTAL\\UNICOMER\\AUTO\\ecosystem-regression/src/test/resources/files/dni.PNG\u0027 into INPUT DOCUMENT FILE","duration":214,"startTime":"2024-02-06T06:51:11.494845-05:00[America/Lima]","screenshots":[{"screenshot":"4dd6f6bf88b52b5bd75e0a163001d0cd0b78d41f22257a97ea15347437ac6750.png","htmlSource":"pagesource8023199347971337736.html","timeStamp":1707220271552,"screenshotName":"4dd6f6bf88b52b5bd75e0a163001d0cd0b78d41f22257a97ea15347437ac6750.png"},{"screenshot":"d72f37ac15976ae5b179d7711f45c82226417ae76663a0900b892d0645401a44.png","timeStamp":1707220271709,"screenshotName":"d72f37ac15976ae5b179d7711f45c82226417ae76663a0900b892d0645401a44.png"}],"result":"SUCCESS","precondition":false,"level":3},{"number":91,"description":"admin clicks on CONFIRM FORM AND GO TO THE NEXT STEPS","duration":902,"startTime":"2024-02-06T06:51:19.830400300-05:00[America/Lima]","screenshots":[{"screenshot":"db2381256659f35dddfad609b5bddacfd6cfe593df02aabdbdff0ffa203f25a9.png","htmlSource":"pagesource7595749349078352505.html","timeStamp":1707220280518,"screenshotName":"db2381256659f35dddfad609b5bddacfd6cfe593df02aabdbdff0ffa203f25a9.png"},{"screenshot":"7bb589a339ef6f3ccdca1a81a0104fe13d763dc5c78e0e2f99784b49122d0c23.png","timeStamp":1707220280732,"screenshotName":"7bb589a339ef6f3ccdca1a81a0104fe13d763dc5c78e0e2f99784b49122d0c23.png"}],"result":"SUCCESS","precondition":false,"level":3}]}]},{"number":92,"description":"Then validate the \"Credit application completed!\" that was created","duration":5473,"startTime":"2024-02-06T06:51:32.169452400-05:00[America/Lima]","screenshots":[{"screenshot":"1733adfd3bf64d98c1ab393393c29c69955413842509a1ce9085eab8f43a8954.png","htmlSource":"pagesource10911525389125390526.html","timeStamp":1707220292219,"screenshotName":"1733adfd3bf64d98c1ab393393c29c69955413842509a1ce9085eab8f43a8954.png"},{"screenshot":"ff5169cfea71e8b6a67ce9cff07aa61a25637330a8ebea0592668b78d962762d.png","timeStamp":1707220297642,"screenshotName":"ff5169cfea71e8b6a67ce9cff07aa61a25637330a8ebea0592668b78d962762d.png"}],"result":"SUCCESS","precondition":false,"level":1,"children":[{"number":93,"description":"Then validate message new client should be a string containing \u0027Credit application completed!\u0027","duration":5145,"startTime":"2024-02-06T06:51:32.484427600-05:00[America/Lima]","screenshots":[{"screenshot":"1733adfd3bf64d98c1ab393393c29c69955413842509a1ce9085eab8f43a8954.png","htmlSource":"pagesource16490385631248703004.html","timeStamp":1707220292616,"screenshotName":"1733adfd3bf64d98c1ab393393c29c69955413842509a1ce9085eab8f43a8954.png"},{"screenshot":"ff5169cfea71e8b6a67ce9cff07aa61a25637330a8ebea0592668b78d962762d.png","timeStamp":1707220297629,"screenshotName":"ff5169cfea71e8b6a67ce9cff07aa61a25637330a8ebea0592668b78d962762d.png"}],"result":"SUCCESS","precondition":false,"level":2,"children":[{"number":94,"description":"admin clicks on BUTTON SEARCH CLIENT","duration":920,"startTime":"2024-02-06T06:51:36.692648800-05:00[America/Lima]","screenshots":[{"screenshot":"1733adfd3bf64d98c1ab393393c29c69955413842509a1ce9085eab8f43a8954.png","htmlSource":"pagesource5177285637110370673.html","timeStamp":1707220297321,"screenshotName":"1733adfd3bf64d98c1ab393393c29c69955413842509a1ce9085eab8f43a8954.png"},{"screenshot":"ff5169cfea71e8b6a67ce9cff07aa61a25637330a8ebea0592668b78d962762d.png","timeStamp":1707220297613,"screenshotName":"ff5169cfea71e8b6a67ce9cff07aa61a25637330a8ebea0592668b78d962762d.png"}],"result":"SUCCESS","precondition":false,"level":3}]}]},{"number":95,"description":"And validate the customer is in \"Analysis\"","duration":16366,"startTime":"2024-02-06T06:51:37.644354500-05:00[America/Lima]","screenshots":[{"screenshot":"ff5169cfea71e8b6a67ce9cff07aa61a25637330a8ebea0592668b78d962762d.png","htmlSource":"pagesource15842516559883301904.html","timeStamp":1707220297692,"screenshotName":"ff5169cfea71e8b6a67ce9cff07aa61a25637330a8ebea0592668b78d962762d.png"},{"screenshot":"59938f93b56696d6534094602fb53e4b6a0e86a9926ac6ed7e409fd522e983fc.png","timeStamp":1707220314010,"screenshotName":"59938f93b56696d6534094602fb53e4b6a0e86a9926ac6ed7e409fd522e983fc.png"}],"result":"SUCCESS","precondition":false,"level":1,"children":[{"number":96,"description":"Admin search document created","duration":9006,"startTime":"2024-02-06T06:51:39.718432900-05:00[America/Lima]","screenshots":[{"screenshot":"f0e9dace670763c5a15dd1f25c43e5558ebddaad7654a74922a8597cf6a8e986.png","htmlSource":"pagesource4352734901820075586.html","timeStamp":1707220300337,"screenshotName":"f0e9dace670763c5a15dd1f25c43e5558ebddaad7654a74922a8597cf6a8e986.png"},{"screenshot":"5808d18cce3bcc563caf0fca7535bc12fab875ab4815a4e5e2cc12c4e46a8628.png","timeStamp":1707220308724,"screenshotName":"5808d18cce3bcc563caf0fca7535bc12fab875ab4815a4e5e2cc12c4e46a8628.png"}],"result":"SUCCESS","precondition":false,"level":2,"children":[{"number":97,"description":"admin enters \u0027825126700\u0027 into INSERT DOCUMENT","duration":855,"startTime":"2024-02-06T06:51:42.347346400-05:00[America/Lima]","screenshots":[{"screenshot":"f0e9dace670763c5a15dd1f25c43e5558ebddaad7654a74922a8597cf6a8e986.png","htmlSource":"pagesource10807200842972477251.html","timeStamp":1707220302981,"screenshotName":"f0e9dace670763c5a15dd1f25c43e5558ebddaad7654a74922a8597cf6a8e986.png"},{"screenshot":"b5126e32a0a751ca24583363d678b259b4cd03e320c1b97c17d9755d85c9d4fc.png","timeStamp":1707220303202,"screenshotName":"b5126e32a0a751ca24583363d678b259b4cd03e320c1b97c17d9755d85c9d4fc.png"}],"result":"SUCCESS","precondition":false,"level":3},{"number":98,"description":"admin clicks on BUTTON TO CHECK IF CLIENT ALREADY EXIST","duration":368,"startTime":"2024-02-06T06:51:47.219086500-05:00[America/Lima]","screenshots":[{"screenshot":"7e7a9a8fc1ac3ea4a3cfa1cc5919b2ee4d0ad8b6830201023ba36d5a5ae91624.png","htmlSource":"pagesource16306543419953488407.html","timeStamp":1707220307378,"screenshotName":"7e7a9a8fc1ac3ea4a3cfa1cc5919b2ee4d0ad8b6830201023ba36d5a5ae91624.png"},{"screenshot":"c4ef9d7207f456dc8da9218a2b1ce2522cda6085229ad8e56abede9085e13c72.png","timeStamp":1707220307587,"screenshotName":"c4ef9d7207f456dc8da9218a2b1ce2522cda6085229ad8e56abede9085e13c72.png"}],"result":"SUCCESS","precondition":false,"level":3}]},{"number":99,"description":"Then validate message analysis should be a string containing \u0027Analysis\u0027","duration":5266,"startTime":"2024-02-06T06:51:48.729624700-05:00[America/Lima]","screenshots":[{"screenshot":"5808d18cce3bcc563caf0fca7535bc12fab875ab4815a4e5e2cc12c4e46a8628.png","htmlSource":"pagesource1083553102885945803.html","timeStamp":1707220308766,"screenshotName":"5808d18cce3bcc563caf0fca7535bc12fab875ab4815a4e5e2cc12c4e46a8628.png"},{"screenshot":"59938f93b56696d6534094602fb53e4b6a0e86a9926ac6ed7e409fd522e983fc.png","timeStamp":1707220313996,"screenshotName":"59938f93b56696d6534094602fb53e4b6a0e86a9926ac6ed7e409fd522e983fc.png"}],"result":"SUCCESS","precondition":false,"level":2}]}]}],"userStory":{"id":"emma/jm/uat/regressionJm","storyName":"Regression JM","displayName":"Regression JM","path":"emma/jm/uat/regressionJm","pathElements":[{"name":"emma","description":""},{"name":"jm","description":""},{"name":"uat","description":""},{"name":"regressionJm","description":""}],"type":"feature"},"title":"1. New client with Analysis in Emma JM","description":"","tags":[{"name":"NewClientWithAnalysis","type":"tag","displayName":"NewClientWithAnalysis"},{"name":"Regression","type":"tag","displayName":"Regression"}],"startTime":"2024-02-06T06:48:12.231536500-05:00[America/Lima]","duration":7291,"projectKey":"","driver":"chrome","isManualTestingUpToDate":false,"dataTable":{"headers":["country","store","typeId","documentId","firstName","secondName","firstLastName","secondLastName","gender","birthDate","areaCode","numberMovil","email","marriedStatus","dependsNumber","address","frecuencyPaid","income","occupation","companyName","employStartDate","companyParish","companyDistrict","jobMainActivity","department","district","streetResidence","referenceResidence","currentDateAddress","residentStatus","employStartDate","nameReference1","relationship1","areaCodeRef","numberReference1","referenceLocation","nameReference2","relationship2","numberReference2","streetWork","message"],"rows":[{"values":["Jamaica","COU JM Port Maria","TRN","825126700","JULIO","RAUL","SAlINAS","GALVEZ","Male","2001-JAN-15","876","1598788","r@g.c","Common Law","3","79-80 A SUPER ROAD","Fortnightly","2000","Civil Servant","UNICOMER SAC","2020-MAY-7","Manchester","Coleyville","Commisions","St Andre","Content Gap","X5X9+QQQ, LAS VEGAS","What is D\u0026Bs","2021-JAN-1","Rent","2020-MAY-7","HERNAN PAREDES","Coworker","876","1593645","79 -81a Road UNITED","JULIAN ALVAREZ","Father","3697415","PRINCIPAL STREET","Credit application completed!"],"lineNumber":18,"result":"SUCCESS"}],"predefinedRows":true,"scenarioOutline":"Given DataTable customer data\n\rGiven the user into EMMA in \"\u003ccountry\u003e\" with credentials\n\rAnd select the country emma\n\rAnd select the store in emma\n\rWhen validate the document ID dose not exist\n\rAnd user enter basic information for Document validation section\n\rThen validate the \"\u003cmessage\u003e\" that was created\n\rAnd validate the customer is in \"Analysis\"\n\r","dataSetDescriptors":[{"startRow":0,"rowCount":0,"name":"","description":""}]},"manual":false,"testSource":"Cucumber","actors":[{"name":"admin","can":["browse the web"]}],"order":0,"result":"SUCCESS","scenarioOutline":"Given DataTable customer data\r\n|typeId | documentId | store | firstName | secondName | firstLastName | secondLastName | numberMovil | email | birthDate | areaCode | gender | dependsNumber | marriedStatus | address | frecuencyPaid | income | occupation | companyName | mployStartDate | companyParish | companyDistrict | jobMainActivity | department | district | streetResidence | referenceResidence | currentDateAddress | residentStatus | employStartDate | nameReference1 | relationship1 | areaCodeRef | numberReference1 | referenceLocation | nameReference2 | relationship2 | numberReference2 | streetWork|\r\n|\u003ctypeId\u003e | \u003cdocumentId\u003e | \u003cstore\u003e | \u003cfirstName\u003e | \u003csecondName\u003e | \u003cfirstLastName\u003e | \u003csecondLastName\u003e | \u003cnumberMovil\u003e | \u003cemail\u003e | \u003cbirthDate\u003e | \u003careaCode\u003e | \u003cgender\u003e | \u003cdependsNumber\u003e | \u003cmarriedStatus\u003e | \u003caddress\u003e | \u003cfrecuencyPaid\u003e | \u003cincome\u003e | \u003coccupation\u003e | \u003ccompanyName\u003e | \u003cemployStartDate\u003e | \u003ccompanyParish\u003e | \u003ccompanyDistrict\u003e | \u003cjobMainActivity\u003e | \u003cdepartment\u003e | \u003cdistrict\u003e | \u003cstreetResidence\u003e | \u003creferenceResidence\u003e | \u003ccurrentDateAddress\u003e | \u003cresidentStatus\u003e | \u003cemployStartDate\u003e | \u003cnameReference1\u003e | \u003crelationship1\u003e | \u003careaCodeRef\u003e | \u003cnumberReference1\u003e | \u003creferenceLocation\u003e | \u003cnameReference2\u003e | \u003crelationship2\u003e | \u003cnumberReference2\u003e | \u003cstreetWork\u003e|\r\nGiven the user into EMMA in \"\u003ccountry\u003e\" with credentials\r\nAnd select the country emma\r\nAnd select the store in emma\r\nWhen validate the document ID dose not exist\r\nAnd user enter basic information for Document validation section\r\nThen validate the \"\u003cmessage\u003e\" that was created\r\nAnd validate the customer is in \"Analysis\""}